setup.py
searchtester/__init__.py
searchtester/core.py
searchtester/scoring.py
searchtester/tests.py
searchtester.egg-info/PKG-INFO
searchtester.egg-info/SOURCES.txt
searchtester.egg-info/dependency_links.txt
searchtester.egg-info/entry_points.txt
searchtester.egg-info/requires.txt
searchtester.egg-info/top_level.txt