Metadata-Version: 1.0
Name: searchtester
Version: 0.6
Summary: Simple system for testing search results, and using that to measure effectiveness of your current search ranking
Home-page: UNKNOWN
Author: James Aylett
Author-email: james@tartarus.org
License: MIT
Platform: UNKNOWN
Classifier: Intended Audience :: Developers
Classifier: Environment :: Console
Classifier: License :: OSI Approved :: MIT License
Classifier: Programming Language :: Python :: 2
Classifier: Topic :: Internet :: WWW/HTTP :: Indexing/Search
Classifier: Topic :: Software Development :: Quality Assurance
Classifier: Topic :: Software Development :: Testing
